LICENSE
README.md
setup.py
pysvgenius/__init__.py
pysvgenius/main.py
pysvgenius.egg-info/PKG-INFO
pysvgenius.egg-info/SOURCES.txt
pysvgenius.egg-info/dependency_links.txt
pysvgenius.egg-info/requires.txt
pysvgenius.egg-info/top_level.txt
pysvgenius/common/__init__.py
pysvgenius/common/config.py
pysvgenius/common/registry.py
pysvgenius/common/utils.py
pysvgenius/converter/__init__.py
pysvgenius/converter/base.py
pysvgenius/converter/contour_based_vectorization.py
pysvgenius/converter/vtracer_binary_search.py
pysvgenius/converter/vtracer_grid_search.py
pysvgenius/generator/__init__.py
pysvgenius/generator/base.py
pysvgenius/generator/sdxl_turbo_generator.py
pysvgenius/generator/stable_diffusion_v2_generator.py
pysvgenius/optimizer/__init__.py
pysvgenius/optimizer/base.py
pysvgenius/optimizer/diffvg_optimizer.py
pysvgenius/optimizer/components/__init__.py
pysvgenius/optimizer/components/aesthetic_evaluator_torch.py
pysvgenius/optimizer/components/image_processor_torch.py
pysvgenius/ranker/__init__.py
pysvgenius/ranker/aesthetic_ranker.py
pysvgenius/ranker/base.py
pysvgenius/ranker/paligemma_ranker.py
pysvgenius/ranker/siglip_ranker.py
pysvgenius/utils/__init__.py
pysvgenius/utils/image_utils.py
pysvgenius/utils/logger.py
pysvgenius/utils/svg_utils.py