Metadata-Version: 2.4
Name: pysvgenius
Version: 0.1.7
Summary: A library for text_to_svg, image_to_svg, and SVG resizing and optimization.
Home-page: https://github.com/tamchamchi/pysvgenius
Author: Anh Nguyen
Author-email: anhndt.work@gmail.com
License: MIT
Project-URL: Bug Tracker, https://github.com/tamchamchi/pysvgenius/issues
Project-URL: Documentation, https://github.com/tamchamchi/pysvgenius#readme
Classifier: License :: OSI Approved :: MIT License
Classifier: Programming Language :: Python :: 3
Classifier: Programming Language :: Python :: 3.10
Classifier: Programming Language :: Python :: 3.11
Requires-Python: >=3.10
License-File: LICENSE
Requires-Dist: accelerate<2.0,>=1.0
Requires-Dist: antlr4-python3-runtime==4.9.3
Requires-Dist: beautifulsoup4>=4.12
Requires-Dist: bitsandbytes>=0.46.0
Requires-Dist: bleach>=6.1
Requires-Dist: cairocffi>=1.6
Requires-Dist: CairoSVG>=2.8
Requires-Dist: certifi>=2024.2
Requires-Dist: cffi>=1.15
Requires-Dist: charset-normalizer>=3.0
Requires-Dist: coloredlogs>=15.0
Requires-Dist: contourpy>=1.2
Requires-Dist: cryptography>=41.0
Requires-Dist: cssselect2>=0.7
Requires-Dist: cycler>=0.12
Requires-Dist: defusedxml>=0.7
Requires-Dist: diffusers>=0.32
Requires-Dist: docutils>=0.21
Requires-Dist: filelock>=3.12
Requires-Dist: fonttools>=4.50
Requires-Dist: fsspec>=2024.3
Requires-Dist: ftfy>=6.1
Requires-Dist: greenlet>=3.0
Requires-Dist: huggingface-hub>=0.32
Requires-Dist: humanfriendly>=10.0
Requires-Dist: imageio>=2.34
Requires-Dist: imageio-ffmpeg>=0.5
Requires-Dist: iopath>=0.1
Requires-Dist: Jinja2>=3.1
Requires-Dist: jsonpatch>=1.32
Requires-Dist: jsonpointer>=2.4
Requires-Dist: jeepney>=0.9
Requires-Dist: keyring>=24.0
Requires-Dist: kiwisolver>=1.4
Requires-Dist: kmeans-gpu>=0.0.5
Requires-Dist: kornia>=0.7
Requires-Dist: kornia_rs>=0.1.5
Requires-Dist: lazy_loader>=0.3
Requires-Dist: llvmlite>=0.43
Requires-Dist: lxml>=4.9
Requires-Dist: markdown-it-py>=3.0
Requires-Dist: MarkupSafe>=2.1
Requires-Dist: matplotlib>=3.8
Requires-Dist: mdurl>=0.1
Requires-Dist: more-itertools>=10.0
Requires-Dist: mpmath>=1.3
Requires-Dist: networkx>=3.2
Requires-Dist: nh3>=0.2
Requires-Dist: numpy<2.0,>=1.26
Requires-Dist: omegaconf>=2.3
Requires-Dist: opencv-python>=4.8
Requires-Dist: pandas>=2.2
Requires-Dist: pillow>=10.2
Requires-Dist: pluggy>=1.4
Requires-Dist: portalocker>=3.1
Requires-Dist: protobuf>=5.26
Requires-Dist: pyaml>=24.0
Requires-Dist: pycparser>=2.21
Requires-Dist: pyparsing>=3.1
Requires-Dist: pytest>=8.1
Requires-Dist: python-dotenv>=1.0
Requires-Dist: python-slugify>=8.0
Requires-Dist: pytz>=2024.1
Requires-Dist: PyYAML>=6.0
Requires-Dist: readme_renderer>=43
Requires-Dist: regex>=2024.0
Requires-Dist: requests>=2.31
Requires-Dist: requests-toolbelt>=1.0
Requires-Dist: rfc3986>=2.0
Requires-Dist: rich>=13.0
Requires-Dist: safetensors>=0.4
Requires-Dist: scikit-image<0.23,>=0.21
Requires-Dist: scipy<1.14,>=1.10
Requires-Dist: scour>=0.38
Requires-Dist: seaborn>=0.13
Requires-Dist: SecretStorage>=3.3
Requires-Dist: sentencepiece>=0.2
Requires-Dist: SQLAlchemy>=2.0
Requires-Dist: sympy>=1.12
Requires-Dist: text-unidecode>=1.3
Requires-Dist: tifffile>=2023.12
Requires-Dist: tinycss2>=1.2
Requires-Dist: tokenizers>=0.19
Requires-Dist: tomli>=2.0
Requires-Dist: torch>=2.1
Requires-Dist: torchaudio>=2.1
Requires-Dist: torchvision>=0.18
Requires-Dist: tqdm>=4.66
Requires-Dist: transformers>=4.40
Requires-Dist: triton>=3.0
Requires-Dist: ttools>=0.1
Requires-Dist: twine>=5.0
Requires-Dist: tzdata>=2024.1
Requires-Dist: urllib3>=2.2
Requires-Dist: vtracer>=0.6
Requires-Dist: webencodings>=0.5
Requires-Dist: websocket-client>=1.7
Provides-Extra: diffvg
Provides-Extra: clip
Provides-Extra: diff-jpeg
Dynamic: author
Dynamic: author-email
Dynamic: classifier
Dynamic: description
Dynamic: description-content-type
Dynamic: home-page
Dynamic: license
Dynamic: license-file
Dynamic: project-url
Dynamic: provides-extra
Dynamic: requires-dist
Dynamic: requires-python
Dynamic: summary
